drf_user/__init__.py
drf_user/admin.py
drf_user/apps.py
drf_user/auth.py
drf_user/managers.py
drf_user/models.py
drf_user/serializers.py
drf_user/urls.py
drf_user/utils.py
drf_user/variables.py
drf_user/views.py
drf_user/migrations/0001_initial.py
drf_user/migrations/0002_user_is_staff.py
drf_user/migrations/0003_auto_20180919_1516.py
drf_user/migrations/0004_auto_20181015_1551.py
drf_user/migrations/0005_auto_20181123_0657.py
drf_user/migrations/0006_auto_20181220_1911.py
drf_user/migrations/0007_auto_20201031_2020.py
drf_user/migrations/0008_auto_20210118_1304.py
drf_user/migrations/__init__.py
drf_user/signals/__init__.py
drf_user/signals/handlers.py
drf_user-1.1.0.dist-info/LICENSE
drf_user-1.1.0.dist-info/METADATA
drf_user-1.1.0.dist-info/WHEEL
drf_user-1.1.0.dist-info/top_level.txt
drf_user-1.1.0.dist-info/RECORD
