Metadata-Version: 2.1
Name: drf-user
Version: 1.1.0
Summary: User APP for Django REST Framework with API Views
Home-page: https://github.com/101loop/drf-user
Author: Himanshu Shankar
Author-email: me@himanshus.com
Maintainer: Sumit Singh
Maintainer-email: sumit.singh4613@gmail.com
License: GPLv3
Platform: UNKNOWN
Classifier: Development Status :: 5 - Production/Stable
Classifier: Environment :: Web Environment
Classifier: Framework :: Django
Classifier: Framework :: Django :: 2.2
Classifier: Framework :: Django :: 3.1
Classifier: Framework :: Django :: 3.2
Classifier: Intended Audience :: Developers
Classifier: License :: OSI Approved :: GNU General Public License v3 (GPLv3)
Classifier: Operating System :: OS Independent
Classifier: Programming Language :: Python
Classifier: Programming Language :: Python :: 3
Classifier: Programming Language :: Python :: 3.6
Classifier: Programming Language :: Python :: 3.7
Classifier: Programming Language :: Python :: 3.8
Classifier: Programming Language :: Python :: 3.9
Classifier: Topic :: Software Development :: Libraries
Classifier: Topic :: Internet :: WWW/HTTP
Requires-Python: >=3.6
License-File: LICENSE
Requires-Dist: Django (>=1.11)
Requires-Dist: django-filter (==2.4.0)
Requires-Dist: djangorestframework (>=3.8.0)
Requires-Dist: djangorestframework-simplejwt (>=4.4.0)
Requires-Dist: drfaddons (>=0.1.0)
Requires-Dist: Pillow (>=7.2.0)
